lab3/muldiv/muldiv.srcs/sources_1/new/multiplier.v
`timescale 1ns / 1ps
//////////////////////////////////////////////////////////////////////////////////
// Company: 
// Engineer: 
// 
// Create Date: 2023/03/28 22:43:58
// Design Name: 
// Module Name: multiplier
// Project Name: 
// Target Devices: 
// Tool Versions: 
// Description: 
// 
// Dependencies: 
// 
// Revision:
// Revision 0.01 - File Created
// Additional Comments:
// 
//////////////////////////////////////////////////////////////////////////////////


module multiplier(
   input clk,
   input start,
   input[31:0] A,
   input[31:0] B,
   output reg finish,
   output reg[63:0] res
);

   reg state; // 记录 multiplier 是不是正在进行运算
   reg[31:0] multiplicand; // 保存当前运算中的被乘数
   wire[31:0] add_high = multiplicand[31:0] + res[63:32];

   reg[5:0] cnt; // 记录当前计算已经经历了几个周期（运算与移位）
   wire[5:0] cnt_next = cnt + 6'b1;

   reg sign = 0; // 记录当前运算的结果是否是负数
   
   assign judgefin = (cnt == 32);

   initial begin
      res <= 0;
      state <= 0;
      finish <= 0;
      cnt <= 0;
      multiplicand <= 0;
   end

   // 使用 V3 乘法器
   always @(posedge clk) begin
      if (judgefin) begin
         // 得到结果
         if (sign) begin
            res <= -res;
         end
         cnt <= 0;
         state <= 0;
         finish <= 1;
      end
      
      if (~state && start) begin
         // Not Running
         sign <= A[31] ^ B[31];
         if (A[31]) begin
            multiplicand <= -A;
         end else begin
            multiplicand <= A;
         end
         if (B[31]) begin
            res <= {32'b0, -B};
         end else begin
            res <= {32'b0, B};
         end
         state <= 1;
         finish <= 0;
         cnt <= 0;
      end else if (state && ~judgefin) begin
         // Running
         // Why not "else"?
         // 因为在 state 和 start 同时为 0 的时候，我们不希望进入这个分支
         // 你需要在这里处理“一次”运算与移位
         cnt <= cnt_next;
         if (res[0]) begin
            res <= {1'b0, add_high, res[31:1]};
         end else begin
            res <= res >> 1;
         end
      end
   end

endmodule

lab3/muldiv/muldiv.srcs/sim_1/new/multiplier_tb.v
`timescale 1ns / 1ps
//////////////////////////////////////////////////////////////////////////////////
// Company: 
// Engineer: 
// 
// Create Date: 2023/03/28 23:24:08
// Design Name: 
// Module Name: multiplier_tb
// Project Name: 
// Target Devices: 
// Tool Versions: 
// Description: 
// 
// Dependencies: 
// 
// Revision:
// Revision 0.01 - File Created
// Additional Comments:
// 
//////////////////////////////////////////////////////////////////////////////////


module multiplier_tb;

  reg clk, start;
  reg[31:0] A;
  reg[31:0] B;

  wire finish;
  wire[63:0] res;

  multiplier m0(.clk(clk), .start(start), .A(A), .B(B), .finish(finish), .res(res));

  initial begin
    $dumpfile("multiplier_signed.vcd");
    $dumpvars(0, multiplier_tb);

    clk = 0;
    start = 0;
    #10;
    A = 32'd1;
    B = 32'd0;
    #10 start = 1;
    #10 start = 0;
    #300;

    A = 32'd0;
    B = 32'd30;
    #10 start = 1;
    #10 start = 0;
    #300;

    A = 32'd10;
    B = 32'd30;
    #10 start = 1;
    #10 start = 0;
    #300;

    A = 32'd66;
    B = 32'd23;
    #10 start = 1;
    #10 start = 0;
    #300;

    A = -32'd10;
    B = 32'd30;
    #10 start = 1;
    #10 start = 0;
    #300;

    A = -32'd10;
    B = -32'd30;
    #10 start = 1;
    #10 start = 0;
    #300;

    A = 32'h7FFFFFFF;
    B = 32'h7FFFFFFF;
    #10 start = 1;
    #10 start = 0;
    #300;

    A = 32'hFFFFFFFF;
    B = 32'hFFFFFFFF;
    #10 start = 1;
    #10 start = 0;
    #500;
    $finish();
  end

  always begin
    #2 clk = ~clk;
  end

endmodule

lab3/muldiv/muldiv.sim/sim_1/behav/xsim/multiplier_signed.vcd
$date
   Wed Apr 12 22:43:25 2023
$end
$version
  2022.2
$end
$timescale
  1ps
$end
$scope module multiplier_tb $end
$var reg 1 ! clk $end
$var reg 1 " start $end
$var reg 32 # A [31:0] $end
$var reg 32 $ B [31:0] $end
$var wire 1 % finish $end
$var wire 64 & res [63:0] $end
$scope module m0 $end
$var wire 1 ' clk $end
$var wire 1 ( start $end
$var wire 32 ) A [31:0] $end
$var wire 32 * B [31:0] $end
$var reg 1 + finish $end
$var reg 64 , res [63:0] $end
$var reg 1 - state $end
$var reg 32 . multiplicand [31:0] $end
$var wire 32 / add_high [31:0] $end
$var reg 6 0 cnt [5:0] $end
$var wire 6 1 cnt_next [5:0] $end
$var reg 1 2 sign $end
$var wire 1 3 judgefin $end
$upscope $end
$upscope $end
$enddefinitions $end
#0
$dumpvars
0!
0"
bx #
bx $
0%
b0 &
0'
0(
bx )
bx *
0+
b0 ,
0-
b0 .
b0 /
b0 0
b1 1
02
03
$end
#2000
1!
1'
#4000
0!
0'
#6000
1!
1'
#8000
0!
0'
#10000
1!
b1 #
b0 $
1'
b1 )
b0 *
#12000
0!
0'
#14000
1!
1'
#16000
0!
0'
#18000
1!
1'
#20000
0!
1"
0'
1(
#22000
1!
1'
1-
b1 .
b1 /
#24000
0!
0'
#26000
1!
1'
b1 0
b10 1
#28000
0!
0'
#30000
1!
0"
1'
0(
b10 0
b11 1
#32000
0!
0'
#34000
1!
1'
b11 0
b100 1
#36000
0!
0'
#38000
1!
1'
b100 0
b101 1
#40000
0!
0'
#42000
1!
1'
b101 0
b110 1
#44000
0!
0'
#46000
1!
1'
b110 0
b111 1
#48000
0!
0'
#50000
1!
1'
b111 0
b1000 1
#52000
0!
0'
#54000
1!
1'
b1000 0
b1001 1
#56000
0!
0'
#58000
1!
1'
b1001 0
b1010 1
#60000
0!
0'
#62000
1!
1'
b1010 0
b1011 1
#64000
0!
0'
#66000
1!
1'
b1011 0
b1100 1
#68000
0!
0'
#70000
1!
1'
b1100 0
b1101 1
#72000
0!
0'
#74000
1!
1'
b1101 0
b1110 1
#76000
0!
0'
#78000
1!
1'
b1110 0
b1111 1
#80000
0!
0'
#82000
1!
1'
b1111 0
b10000 1
#84000
0!
0'
#86000
1!
1'
b10000 0
b10001 1
#88000
0!
0'
#90000
1!
1'
b10001 0
b10010 1
#92000
0!
0'
#94000
1!
1'
b10010 0
b10011 1
#96000
0!
0'
#98000
1!
1'
b10011 0
b10100 1
#100000
0!
0'
#102000
1!
1'
b10100 0
b10101 1
#104000
0!
0'
#106000
1!
1'
b10101 0
b10110 1
#108000
0!
0'
#110000
1!
1'
b10110 0
b10111 1
#112000
0!
0'
#114000
1!
1'
b10111 0
b11000 1
#116000
0!
0'
#118000
1!
1'
b11000 0
b11001 1
#120000
0!
0'
#122000
1!
1'
b11001 0
b11010 1
#124000
0!
0'
#126000
1!
1'
b11010 0
b11011 1
#128000
0!
0'
#130000
1!
1'
b11011 0
b11100 1
#132000
0!
0'
#134000
1!
1'
b11100 0
b11101 1
#136000
0!
0'
#138000
1!
1'
b11101 0
b11110 1
#140000
0!
0'
#142000
1!
1'
b11110 0
b11111 1
#144000
0!
0'
#146000
1!
1'
b11111 0
b100000 1
#148000
0!
0'
#150000
1!
1'
b100000 0
b100001 1
13
#152000
0!
0'
#154000
1!
1%
1'
1+
0-
b0 0
b1 1
03
